gslpy/__init__.py
gslpy-0.0.0.dist-info/METADATA
gslpy-0.0.0.dist-info/WHEEL
gslpy-0.0.0.dist-info/top_level.txt
gslpy-0.0.0.dist-info/RECORD
