Metadata-Version: 2.1
Name: gslpy
Version: 0.0.0
Summary: GNU Scientific Library for Python
Home-page: UNKNOWN
Author: André Bienemann
Author-email: andre.bienemann@gmail.com
License: UNKNOWN
Platform: UNKNOWN
